seamapi/__init__.py
seamapi/access_codes.py
seamapi/action_attempts.py
seamapi/climate_setting_schedules.py
seamapi/connect_webviews.py
seamapi/connected_accounts.py
seamapi/devices.py
seamapi/events.py
seamapi/locks.py
seamapi/noise_sensors.py
seamapi/noise_thresholds.py
seamapi/routes.py
seamapi/seam.py
seamapi/thermostats.py
seamapi/types.py
seamapi/utils/__init__.py
seamapi/utils/convert_to_id.py
seamapi/utils/deep_attr_dict.py
seamapi/utils/get_sentry_dsn.py
seamapi/utils/parse_list_device_params.py
seamapi/utils/report_error.py
seamapi/webhooks.py
seamapi/workspaces.py
seamapi-3.0.0.dist-info/METADATA
seamapi-3.0.0.dist-info/WHEEL
seamapi-3.0.0.dist-info/RECORD
