Metadata-Version: 2.1
Name: seamapi
Version: 3.0.0
Summary: A Python Library for Seam's API https://getseam.com
License: MIT
Author: Severin Ibarluzea
Author-email: seveibar@gmail.com
Requires-Python: >=3.7,<4.0
Classifier: License :: OSI Approved :: MIT License
Classifier: Programming Language :: Python :: 3
Classifier: Programming Language :: Python :: 3.7
Classifier: Programming Language :: Python :: 3.8
Classifier: Programming Language :: Python :: 3.9
Classifier: Programming Language :: Python :: 3.10
Classifier: Programming Language :: Python :: 3.11
Requires-Dist: dataclasses-json (>=0.5.6,<0.6.0)
Requires-Dist: requests (>=2.26.0,<3.0.0)
Requires-Dist: sentry-sdk (>=1.9.10,<2.0.0)
